consul/__init__.py
consul/aio.py
consul/base.py
consul/std.py
consul/tornado.py
consul/twisted.py
python_consul-1.0.0.dist-info/METADATA
python_consul-1.0.0.dist-info/RECORD
python_consul-1.0.0.dist-info/WHEEL
python_consul-1.0.0.dist-info/top_level.txt
